bamboo_ipa_sync/__init__.py
bamboo_ipa_sync/__main__.py
bamboo_ipa_sync/__version__.py
bamboo_ipa_sync/bamboo_ipa_sync.py
bamboo_ipa_sync-3.1.0.dist-info/DESCRIPTION.rst
bamboo_ipa_sync-3.1.0.dist-info/METADATA
bamboo_ipa_sync-3.1.0.dist-info/RECORD
bamboo_ipa_sync-3.1.0.dist-info/WHEEL
bamboo_ipa_sync-3.1.0.dist-info/entry_points.txt
bamboo_ipa_sync-3.1.0.dist-info/metadata.json
bamboo_ipa_sync-3.1.0.dist-info/top_level.txt
