Metadata-Version: 2.0
Name: bamboo-ipa-sync
Version: 3.1.0
Summary: Tool to synchronise FreeIPA with BambooHR
Home-page: https://github.com/peterpakos/bamboo_ipa_sync
Author: Peter Pakos
Author-email: peter.pakos@wandisco.com
License: UNKNOWN
Keywords: python template
Platform: UNKNOWN
Classifier: Programming Language :: Python :: 2
Classifier: Programming Language :: Python :: 2.7
Classifier: Programming Language :: Python :: 3
Classifier: Programming Language :: Python :: 3.4
Classifier: Programming Language :: Python :: 3.5
Classifier: Programming Language :: Python :: 3.6
Classifier: Programming Language :: Python :: 3.7
Classifier: Topic :: System :: Systems Administration :: Authentication/Directory :: LDAP
Requires-Dist: pplogger
Requires-Dist: ppipa
Requires-Dist: ppmail
Requires-Dist: ppconfig
Requires-Dist: ppbamboo
Requires-Dist: tzlocal
Requires-Dist: prettytable
